sdk/__init__.py
sdk/sdk.py
sdk/sdkconfiguration.py
sdk/_hooks/__init__.py
sdk/_hooks/sdkhooks.py
sdk/_hooks/types.py
sdk/models/__init__.py
sdk/models/components/__init__.py
sdk/models/components/agent.py
sdk/models/components/agentnodefaultnorequired.py
sdk/models/components/agentpromptparams.py
sdk/models/components/calldetail.py
sdk/models/components/callphonenumber.py
sdk/models/components/phonenumber.py
sdk/models/components/security.py
sdk/models/errors/__init__.py
sdk/models/errors/createagent.py
sdk/models/errors/createphonecall.py
sdk/models/errors/createphonenumber.py
sdk/models/errors/deleteagent.py
sdk/models/errors/deletephonenumber.py
sdk/models/errors/getagent.py
sdk/models/errors/getcall.py
sdk/models/errors/getphonenumber.py
sdk/models/errors/listagents.py
sdk/models/errors/listcalls.py
sdk/models/errors/listphonenumbers.py
sdk/models/errors/sdkerror.py
sdk/models/errors/updateagent.py
sdk/models/errors/updatephoneagent.py
sdk/models/operations/__init__.py
sdk/models/operations/createagent.py
sdk/models/operations/createphonecall.py
sdk/models/operations/createphonenumber.py
sdk/models/operations/deleteagent.py
sdk/models/operations/deletephonenumber.py
sdk/models/operations/getagent.py
sdk/models/operations/getcall.py
sdk/models/operations/getphonenumber.py
sdk/models/operations/listagents.py
sdk/models/operations/listcalls.py
sdk/models/operations/listphonenumbers.py
sdk/models/operations/updateagent.py
sdk/models/operations/updatephoneagent.py
sdk/utils/__init__.py
sdk/utils/retries.py
sdk/utils/utils.py
retell-0.5.1.dist-info/LICENSE.md
retell-0.5.1.dist-info/METADATA
retell-0.5.1.dist-info/WHEEL
retell-0.5.1.dist-info/top_level.txt
retell-0.5.1.dist-info/RECORD
