Metadata-Version: 2.1
Name: retell
Version: 0.5.1
Summary: retell sdk
Home-page: UNKNOWN
Author: retell
License: UNKNOWN
Platform: UNKNOWN
Requires-Python: >=3.8
Provides-Extra: dev
